valid8/__init__.py
valid8/_version.py
valid8/base.py
valid8/common_syntax.py
valid8/composition.py
valid8/entry_points.py
valid8/entry_points_annotations.py
valid8/entry_points_annotations.pyi
valid8/entry_points_inline.py
valid8/py.typed
valid8/utils/__init__.py
valid8/utils/decoration_tools.py
valid8/utils/signature_tools.py
valid8/utils/string_tools.py
valid8/utils/typing_inspect.py
valid8/utils/typing_tools.py
valid8/validation_lib/__init__.py
valid8/validation_lib/collections.py
valid8/validation_lib/comparables.py
valid8/validation_lib/mini_lambda_.py
valid8/validation_lib/numbers.py
valid8/validation_lib/types.py
valid8-5.1.2.dist-info/LICENSE
valid8-5.1.2.dist-info/METADATA
valid8-5.1.2.dist-info/WHEEL
valid8-5.1.2.dist-info/top_level.txt
valid8-5.1.2.dist-info/RECORD
