Metadata-Version: 2.1
Name: valid8
Version: 5.1.2
Summary: Yet another validation lib ;). Provides tools for general-purpose variable validation, function inputs/outputs validation as well as class fields validation. All entry points raise consistent ValidationError including all contextual details, with dynamic inheritance of ValueError/TypeError as appropriate.
Home-page: https://github.com/smarie/python-valid8
Maintainer: Sylvain Marié
Maintainer-email: sylvain.marie@schneider-electric.com
License: BSD 3-Clause
Download-URL: https://github.com/smarie/python-valid8/tarball/5.1.2
Keywords: decorate decorator input arg args argument function contract value check checker valid validate validator validation
Platform: UNKNOWN
Classifier: Development Status :: 5 - Production/Stable
Classifier: Intended Audience :: Developers
Classifier: Topic :: Software Development :: Libraries :: Python Modules
Classifier: License :: OSI Approved :: BSD License
Classifier: Programming Language :: Python :: 2.7
Classifier: Programming Language :: Python :: 3.5
Classifier: Programming Language :: Python :: 3.6
Classifier: Programming Language :: Python :: 3.7
